leukos/__init__.py
leukos/about.py
leukos/components/navbar.py
leukos/leukos.py
leukos/profile.py
leukos/proteins.py
leukos/state.py
leukos-0.0.2.dist-info/LICENSE
leukos-0.0.2.dist-info/METADATA
leukos-0.0.2.dist-info/WHEEL
leukos-0.0.2.dist-info/RECORD
